{
  "accentColor": "{{appsmith.theme.colors.primaryColor}}",
  "allowAddNewRow": false,
  "animateLoading": true,
  "borderColor": "#E0DEDE",
  "borderRadius": "{{appsmith.theme.borderRadius.appBorderRadius}}",
  "borderWidth": "1",
  "bottomRow": 195,
  "boxShadow": "{{appsmith.theme.boxShadow.appBoxShadow}}",
  "cachedTableData": {},
  "canFreezeColumn": true,
  "childStylesheet": {
    "button": {
      "borderRadius": "{{appsmith.theme.borderRadius.appBorderRadius}}",
      "boxShadow": "none",
      "buttonColor": "{{appsmith.theme.colors.primaryColor}}"
    },
    "editActions": {
      "discardBorderRadius": "{{appsmith.theme.borderRadius.appBorderRadius}}",
      "discardButtonColor": "{{appsmith.theme.colors.primaryColor}}",
      "saveBorderRadius": "{{appsmith.theme.borderRadius.appBorderRadius}}",
      "saveButtonColor": "{{appsmith.theme.colors.primaryColor}}"
    },
    "iconButton": {
      "borderRadius": "{{appsmith.theme.borderRadius.appBorderRadius}}",
      "boxShadow": "none",
      "buttonColor": "{{appsmith.theme.colors.primaryColor}}"
    },
    "menuButton": {
      "borderRadius": "{{appsmith.theme.borderRadius.appBorderRadius}}",
      "boxShadow": "none",
      "menuColor": "{{appsmith.theme.colors.primaryColor}}"
    }
  },
  "columnOrder": [
    "iprodid",
    "nama_group",
    "nama",
    "satuan",
    "kemasan",
    "hna",
    "aktif",
    "sku_ecom"
  ],
  "columnUpdatedAt": 1748250060051,
  "columnWidthMap": {
    "aktif": 69,
    "customColumn1": 60,
    "hna": 101,
    "iprodid": 112,
    "kemasan": 107,
    "nama": 466,
    "nama_brand": 88,
    "satuan": 88
  },
  "customIsLoading": false,
  "customIsLoadingValue": "",
  "defaultPageSize": 0,
  "defaultSelectedRowIndex": 0,
  "defaultSelectedRowIndices": [
    0
  ],
  "delimiter": ",",
  "dynamicBindingPathList": [
    {
      "key": "accentColor"
    },
    {
      "key": "borderRadius"
    },
    {
      "key": "boxShadow"
    },
    {
      "key": "tableData"
    },
    {
      "key": "totalRecordsCount"
    },
    {
      "key": "primaryColumns.nama.computedValue"
    },
    {
      "key": "primaryColumns.satuan.computedValue"
    },
    {
      "key": "primaryColumns.kemasan.computedValue"
    },
    {
      "key": "primaryColumns.hna.computedValue"
    },
    {
      "key": "primaryColumns.aktif.computedValue"
    },
    {
      "key": "primaryColumns.iprodid.computedValue"
    },
    {
      "key": "primaryColumns.nama_group.computedValue"
    },
    {
      "key": "primaryColumns.sku_ecom.computedValue"
    }
  ],
  "dynamicPropertyPathList": [
    {
      "key": "tableData"
    }
  ],
  "dynamicTriggerPathList": [
    {
      "key": "onPageChange"
    },
    {
      "key": "onSearchTextChanged"
    },
    {
      "key": "onSort"
    },
    {
      "key": "onAddNewRowSave"
    }
  ],
  "enableClientSideSearch": false,
  "endOfData": false,
  "flexVerticalAlignment": "start",
  "horizontalAlignment": "LEFT",
  "inlineEditingSaveOption": "CUSTOM",
  "isLoading": false,
  "isSortable": true,
  "isVisible": true,
  "isVisibleDownload": true,
  "isVisibleFilters": true,
  "isVisiblePagination": true,
  "isVisibleSearch": true,
  "key": "j6pyrzb81h",
  "label": "Data",
  "leftColumn": 0,
  "minWidth": 450,
  "mobileBottomRow": 30,
  "mobileLeftColumn": 0,
  "mobileRightColumn": 24,
  "mobileTopRow": 2,
  "needsErrorInfo": false,
  "onAddNewRowSave": "{{Insert_iproduk1.run(() => {\n            showAlert(\"Successfully created!\");\n            Select_iproduk1.run()\n          }, () => {\n            showAlert(\"Unable to create!\");\n          })}}",
  "onPageChange": "{{\n            Select_iproduk1.run();\n            Total_record_iproduk1.run()\n          }}",
  "onSearchTextChanged": "{{updateSku.run().catch(() => {\n  showAlert('Nama SKU tidak boleh sama.', 'warning');\n});}}",
  "onSort": "{{\n            Select_iproduk1.run();\n            Total_record_iproduk1.run()\n          }}",
  "parentColumnSpace": 16.5,
  "parentId": "3kg7u6u6nr",
  "parentRowSpace": 10,
  "primaryColumnId": "iprodid",
  "primaryColumns": {
    "aktif": {
      "alias": "aktif",
      "allowCellWrapping": false,
      "allowSameOptionsInNewRow": true,
      "columnType": "text",
      "computedValue": "{{Table2.processedTableData.map((currentRow, currentIndex) => ( currentRow[\"aktif\"]))}}",
      "currencyCode": "USD",
      "decimals": 0,
      "enableFilter": true,
      "enableSort": true,
      "horizontalAlignment": "CENTER",
      "id": "aktif",
      "index": 9,
      "isCellEditable": false,
      "isCellVisible": true,
      "isDerived": false,
      "isDisabled": false,
      "isDiscardVisible": true,
      "isEditable": false,
      "isSaveVisible": true,
      "isVisible": true,
      "label": "Aktif",
      "notation": "standard",
      "originalId": "aktif",
      "sticky": "",
      "textSize": "0.875rem",
      "thousandSeparator": true,
      "validation": {},
      "verticalAlignment": "CENTER",
      "width": 150
    },
    "hna": {
      "alias": "hna",
      "allowCellWrapping": false,
      "allowSameOptionsInNewRow": true,
      "columnType": "currency",
      "computedValue": "{{Table2.processedTableData.map((currentRow, currentIndex) => ( currentRow[\"hna\"]))}}",
      "currencyCode": "IDR",
      "decimals": 0,
      "enableFilter": true,
      "enableSort": true,
      "horizontalAlignment": "RIGHT",
      "id": "hna",
      "index": 7,
      "isCellEditable": false,
      "isCellVisible": true,
      "isDerived": false,
      "isDisabled": false,
      "isDiscardVisible": true,
      "isEditable": false,
      "isSaveVisible": true,
      "isVisible": true,
      "label": "HNA",
      "notation": "standard",
      "originalId": "hna",
      "sticky": "",
      "textSize": "0.875rem",
      "thousandSeparator": true,
      "validation": {},
      "verticalAlignment": "CENTER",
      "width": 150
    },
    "iprodid": {
      "alias": "iprodid",
      "allowCellWrapping": false,
      "allowSameOptionsInNewRow": true,
      "columnType": "text",
      "computedValue": "{{Table2.processedTableData.map((currentRow, currentIndex) => ( currentRow[\"iprodid\"]))}}",
      "currencyCode": "USD",
      "decimals": 0,
      "enableFilter": true,
      "enableSort": true,
      "horizontalAlignment": "LEFT",
      "id": "iprodid",
      "index": 0,
      "isCellEditable": false,
      "isCellVisible": true,
      "isDerived": false,
      "isDisabled": false,
      "isDiscardVisible": true,
      "isEditable": false,
      "isSaveVisible": true,
      "isVisible": true,
      "label": "Produk ID",
      "notation": "standard",
      "originalId": "iprodid",
      "sticky": "",
      "textSize": "0.875rem",
      "thousandSeparator": true,
      "validation": {},
      "verticalAlignment": "CENTER",
      "width": 150
    },
    "kemasan": {
      "alias": "kemasan",
      "allowCellWrapping": false,
      "allowSameOptionsInNewRow": true,
      "columnType": "text",
      "computedValue": "{{Table2.processedTableData.map((currentRow, currentIndex) => ( currentRow[\"kemasan\"]))}}",
      "currencyCode": "USD",
      "decimals": 0,
      "enableFilter": true,
      "enableSort": true,
      "horizontalAlignment": "CENTER",
      "id": "kemasan",
      "index": 5,
      "isCellEditable": false,
      "isCellVisible": true,
      "isDerived": false,
      "isDisabled": false,
      "isDiscardVisible": true,
      "isEditable": false,
      "isSaveVisible": true,
      "isVisible": true,
      "label": "Kemasan",
      "notation": "standard",
      "originalId": "kemasan",
      "sticky": "",
      "textSize": "0.875rem",
      "thousandSeparator": true,
      "validation": {},
      "verticalAlignment": "CENTER",
      "width": 150
    },
    "nama": {
      "alias": "nama",
      "allowCellWrapping": true,
      "allowSameOptionsInNewRow": true,
      "columnType": "text",
      "computedValue": "{{Table2.processedTableData.map((currentRow, currentIndex) => ( currentRow[\"nama\"]))}}",
      "currencyCode": "USD",
      "decimals": 0,
      "enableFilter": true,
      "enableSort": true,
      "horizontalAlignment": "LEFT",
      "id": "nama",
      "index": 1,
      "isCellEditable": false,
      "isCellVisible": true,
      "isDerived": false,
      "isDisabled": false,
      "isDiscardVisible": true,
      "isEditable": false,
      "isSaveVisible": true,
      "isVisible": true,
      "label": "Nama Produk",
      "notation": "standard",
      "originalId": "nama",
      "sticky": "",
      "textSize": "0.875rem",
      "thousandSeparator": true,
      "validation": {},
      "verticalAlignment": "CENTER",
      "width": 150
    },
    "nama_group": {
      "alias": "nama_group",
      "allowCellWrapping": false,
      "allowSameOptionsInNewRow": true,
      "cellBackground": "",
      "columnType": "text",
      "computedValue": "{{Table2.processedTableData.map((currentRow, currentIndex) => ( currentRow[\"nama_group\"]))}}",
      "currencyCode": "USD",
      "decimals": 0,
      "enableFilter": true,
      "enableSort": true,
      "fontStyle": "",
      "horizontalAlignment": "LEFT",
      "id": "nama_group",
      "index": 0,
      "isCellEditable": false,
      "isCellVisible": true,
      "isDerived": false,
      "isDisabled": false,
      "isDiscardVisible": true,
      "isEditable": false,
      "isSaveVisible": true,
      "isVisible": true,
      "label": "Group Brand",
      "notation": "standard",
      "originalId": "nama_group",
      "sticky": "",
      "textColor": "",
      "textSize": "0.875rem",
      "thousandSeparator": true,
      "validation": {},
      "verticalAlignment": "CENTER",
      "width": 150
    },
    "satuan": {
      "alias": "satuan",
      "allowCellWrapping": false,
      "allowSameOptionsInNewRow": true,
      "columnType": "text",
      "computedValue": "{{Table2.processedTableData.map((currentRow, currentIndex) => ( currentRow[\"satuan\"]))}}",
      "currencyCode": "USD",
      "decimals": 0,
      "enableFilter": true,
      "enableSort": true,
      "horizontalAlignment": "CENTER",
      "id": "satuan",
      "index": 4,
      "isCellEditable": false,
      "isCellVisible": true,
      "isDerived": false,
      "isDisabled": false,
      "isDiscardVisible": true,
      "isEditable": false,
      "isSaveVisible": true,
      "isVisible": true,
      "label": "Satuan",
      "notation": "standard",
      "originalId": "satuan",
      "sticky": "",
      "textSize": "0.875rem",
      "thousandSeparator": true,
      "validation": {},
      "verticalAlignment": "CENTER",
      "width": 150
    },
    "sku_ecom": {
      "alias": "sku_ecom",
      "allowCellWrapping": false,
      "allowSameOptionsInNewRow": true,
      "cellBackground": "",
      "columnType": "text",
      "computedValue": "{{Table2.processedTableData.map((currentRow, currentIndex) => ( currentRow[\"sku_ecom\"]))}}",
      "currencyCode": "USD",
      "decimals": 0,
      "enableFilter": true,
      "enableSort": true,
      "fontStyle": "",
      "horizontalAlignment": "LEFT",
      "id": "sku_ecom",
      "index": 8,
      "isCellEditable": true,
      "isCellVisible": true,
      "isDerived": false,
      "isDisabled": false,
      "isDiscardVisible": true,
      "isEditable": true,
      "isSaveVisible": true,
      "isVisible": true,
      "label": "SKU",
      "notation": "standard",
      "originalId": "sku_ecom",
      "sticky": "",
      "textColor": "",
      "textSize": "0.875rem",
      "thousandSeparator": true,
      "validation": {},
      "verticalAlignment": "CENTER",
      "width": 150
    }
  },
  "renderMode": "CANVAS",
  "responsiveBehavior": "fill",
  "rightColumn": 64,
  "searchKey": "",
  "serverSidePaginationEnabled": false,
  "showInlineEditingOptionDropdown": true,
  "tableData": "{{Select_iproduk1.data}}",
  "textSize": "0.875rem",
  "topRow": 0,
  "totalRecordsCount": "{{Total_record_iproduk1.data[0].count}}",
  "type": "TABLE_WIDGET_V2",
  "version": 2,
  "verticalAlignment": "CENTER",
  "widgetId": "3931j65l49",
  "widgetName": "Table2"
}