{
  "gitSyncId": "682ea91b0f42c0201158e75b_762c5e38-b0c7-4313-b88e-6176eac15bf5",
  "id": "Report_utils2.dashboardMetrics",
  "pluginId": "js-plugin",
  "pluginType": "JS",
  "unpublishedAction": {
    "actionConfiguration": {
      "encodeParamsToggle": true,
      "jsArguments": [],
      "paginationType": "NONE",
      "timeoutInMillisecond": 10000
    },
    "collectionId": "Report_utils2",
    "confirmBeforeExecute": false,
    "datasource": {
      "isAutoGenerated": false,
      "name": "UNUSED_DATASOURCE",
      "pluginId": "js-plugin"
    },
    "dynamicBindingPathList": [
      {
        "key": "body"
      }
    ],
    "executeOnLoad": true,
    "fullyQualifiedName": "utils2.dashboardMetrics",
    "name": "dashboardMetrics",
    "pageId": "Report",
    "userSetOnLoad": false
  }
}